{"nodes":[{"id":"1","moduleSize":20.426452891150326,"group":4,"pieChart":[{"color":1,"percent":14.075595727198028},{"color":2,"percent":13.820870994248152},{"color":3,"percent":18.964667214461791},{"color":4,"percent":19.13722267871816},{"color":5,"percent":15.932621199671324},{"color":6,"percent":18.003286770747739}]},{"id":"2","moduleSize":19.572773492588169,"group":4,"pieChart":[{"color":1,"percent":13.988312636961286},{"color":2,"percent":14.037009982955928},{"color":3,"percent":14.864864864864865},{"color":4,"percent":28.755782809836866},{"color":5,"percent":13.915266617969321},{"color":6,"percent":14.414414414414415}]},{"id":"3","moduleSize":11.047575072713155,"group":3,"pieChart":[{"color":1,"percent":8.6419753086419746},{"color":2,"percent":8.0246913580246915},{"color":3,"percent":23.456790123456788},{"color":4,"percent":20.987654320987652},{"color":5,"percent":16.666666666666664},{"color":6,"percent":22.222222222222221}]},{"id":"4","moduleSize":7.2357901567110963,"group":4,"pieChart":[{"color":1,"percent":0},{"color":2,"percent":0},{"color":3,"percent":0},{"color":4,"percent":100},{"color":5,"percent":0},{"color":6,"percent":0}]}], "links":[{"source":1,"target":2,"value":1402},{"source":1,"target":3,"value":6},{"source":2,"target":3,"value":65},{"source":2,"target":4,"value":6}]}